odoo/addons/l10n_it_accompanying_invoice/README.rst
odoo/addons/l10n_it_accompanying_invoice/__init__.py
odoo/addons/l10n_it_accompanying_invoice/__manifest__.py
odoo/addons/l10n_it_accompanying_invoice/i18n/it.po
odoo/addons/l10n_it_accompanying_invoice/i18n/l10n_it_accompanying_invoice.pot
odoo/addons/l10n_it_accompanying_invoice/models/__init__.py
odoo/addons/l10n_it_accompanying_invoice/models/account_invoice.py
odoo/addons/l10n_it_accompanying_invoice/readme/CONTRIBUTORS.rst
odoo/addons/l10n_it_accompanying_invoice/readme/DESCRIPTION.rst
odoo/addons/l10n_it_accompanying_invoice/readme/USAGE.rst
odoo/addons/l10n_it_accompanying_invoice/static/description/icon.png
odoo/addons/l10n_it_accompanying_invoice/static/description/index.html
odoo/addons/l10n_it_accompanying_invoice/tests/__init__.py
odoo/addons/l10n_it_accompanying_invoice/tests/test_report.py
odoo/addons/l10n_it_accompanying_invoice/views/account.xml
odoo/addons/l10n_it_accompanying_invoice/views/report_invoice.xml
odoo12_addon_l10n_it_accompanying_invoice-12.0.1.0.0.99.dev5.dist-info/METADATA
odoo12_addon_l10n_it_accompanying_invoice-12.0.1.0.0.99.dev5.dist-info/WHEEL
odoo12_addon_l10n_it_accompanying_invoice-12.0.1.0.0.99.dev5.dist-info/top_level.txt
odoo12_addon_l10n_it_accompanying_invoice-12.0.1.0.0.99.dev5.dist-info/RECORD
